Metadata-Version: 2.1
Name: Py3Chef
Version: 0.4.0rc5
Summary: Python implementation of a Chef API client.
Home-page: http://github.com/leigh-johnson/pychef
Author: Noah Kantrowitz
Author-email: noah@coderanger.net
Maintainer: Leigh Johnson
Maintainer-email: leigh@bitsy.ai
License: Apache 2.0
Platform: UNKNOWN
Requires-Python: >3.6.9
License-File: LICENSE
Requires-Dist: requests (>=2.7.0)
Requires-Dist: six (>=1.9.0)
